siaplotlib/__init__.py
siaplotlib/chart_building/__init__.py
siaplotlib/chart_building/base_builder.py
siaplotlib/chart_building/interfaces.py
siaplotlib/chart_building/level_chart.py
siaplotlib/chart_building/line_chart.py
siaplotlib/charts/__init__.py
siaplotlib/charts/base_chart.py
siaplotlib/charts/interfaces.py
siaplotlib/charts/level_chart.py
siaplotlib/charts/line_chart.py
siaplotlib/charts/raw_image.py
siaplotlib/processing/__init__.py
siaplotlib/processing/aggregation.py
siaplotlib/processing/computations.py
siaplotlib/processing/parallelism.py
siaplotlib/processing/wrangling.py
siaplotlib/utils/exceptions.py
siaplotlib/utils/log.py
siaplotlib-0.2.1.dist-info/LICENCE
siaplotlib-0.2.1.dist-info/METADATA
siaplotlib-0.2.1.dist-info/WHEEL
siaplotlib-0.2.1.dist-info/top_level.txt
siaplotlib-0.2.1.dist-info/RECORD
