Metadata-Version: 2.1
Name: siaplotlib
Version: 0.2.1
Summary: Provide an easy to use interface for plotting oceanographic data.
Author: Alexis Montejo et al.
Maintainer: SIA Project
Project-URL: Homepage, https://sia-information-system.github.io/sia-website
Project-URL: Source Code, https://github.com/sia-information-system/siaplotlib
Keywords: gis,cartography,oceanographic,oceanic,data,visualization
Requires-Python: >=3.10
License-File: LICENCE
Requires-Dist: numpy (>=1.23.4)
Requires-Dist: pandas (>=1.5.1)
Requires-Dist: xarray (>=2022.11.0)
Requires-Dist: matplotlib (>=3.6.2)
Requires-Dist: pillow (>=9.3.0)
Requires-Dist: cartopy (==0.21.1)
Requires-Dist: windrose (>=1.8.1)
Provides-Extra: dev
Requires-Dist: bumpver ; extra == 'dev'
Requires-Dist: netcdf4 (==1.6.2) ; extra == 'dev'
Requires-Dist: build ; extra == 'dev'
Requires-Dist: twine ; extra == 'dev'
